django_declarative_apis/__init__.py
django_declarative_apis/adapters.py
django_declarative_apis/events.py
django_declarative_apis/models.py
django_declarative_apis/authentication/__init__.py
django_declarative_apis/authentication/errors.py
django_declarative_apis/authentication/oauthlib/__init__.py
django_declarative_apis/authentication/oauthlib/endpoint.py
django_declarative_apis/authentication/oauthlib/oauth1.py
django_declarative_apis/authentication/oauthlib/oauth_errors.py
django_declarative_apis/authentication/oauthlib/request_validator.py
django_declarative_apis/machinery/__init__.py
django_declarative_apis/machinery/attributes.py
django_declarative_apis/machinery/errors.py
django_declarative_apis/machinery/filtering.py
django_declarative_apis/machinery/tasks.py
django_declarative_apis/machinery/utils.py
django_declarative_apis/management/__init__.py
django_declarative_apis/management/commands/__init__.py
django_declarative_apis/management/commands/gendocs.py
django_declarative_apis/migrations/0001_initial.py
django_declarative_apis/migrations/0002_add_consumer_type_field.py
django_declarative_apis/migrations/__init__.py
django_declarative_apis/resources/__init__.py
django_declarative_apis/resources/emitters.py
django_declarative_apis/resources/resource.py
django_declarative_apis/resources/utils.py
django_declarative_apis-0.34.2.dist-info/licenses/AUTHORS
django_declarative_apis-0.34.2.dist-info/licenses/LICENSE
django_declarative_apis-0.34.2.dist-info/METADATA
django_declarative_apis-0.34.2.dist-info/WHEEL
django_declarative_apis-0.34.2.dist-info/top_level.txt
django_declarative_apis-0.34.2.dist-info/RECORD
