Metadata-Version: 2.4
Name: django-declarative-apis
Version: 0.34.2
Summary: Simple, readable, declarative APIs for Django
Keywords: django,rest,declarative,api
Classifier: Development Status :: 3 - Alpha
Classifier: Environment :: Web Environment
Classifier: Framework :: Django
Classifier: Intended Audience :: Developers
Classifier: License :: OSI Approved :: MIT License
Classifier: Operating System :: OS Independent
Classifier: Programming Language :: Python
Classifier: Topic :: Internet :: WWW/HTTP
License-File: LICENSE
License-File: AUTHORS
Requires-Dist: Django<6,>=4.2
Requires-Dist: celery!=4.1.0,>=4.0.2
Requires-Dist: cryptography>=2.0
Requires-Dist: decorator==4.0.11
Requires-Dist: django-dirtyfields>=1.2.1
Requires-Dist: oauthlib[rsa,signedtoken]>=3.1.0
Requires-Dist: pydantic>=1.8
Provides-Extra: dev
Requires-Dist: bandit>=1.7.4; extra == "dev"
Requires-Dist: bumpversion~=0.5; extra == "dev"
Requires-Dist: coverage[toml]==6.3.2; extra == "dev"
Requires-Dist: ipython~=7.0; extra == "dev"
Requires-Dist: oauth2==1.9.0.post1; extra == "dev"
Requires-Dist: pyyaml~=6.0; extra == "dev"
Requires-Dist: ruff~=0.1.2; extra == "dev"
Requires-Dist: sphinx_rtd_theme==3.0.2; extra == "dev"
Requires-Dist: tblib~=1.6.0; extra == "dev"
Dynamic: license-file
